{
  "id": "60e2df352ac4725cb2a0f9f9",
  "datasetId": "60e2dab1c09a7cbd614ec5bb",
  "createdAt": "2021-07-05T10:30:13.000Z",
  "dir": "/",
  "filename": "/anchored-boats-ocean-nautical-sailboat-b-2047077.jpg",
  "type": "file",
  "hidden": false,
  "metadata": {
    "system": {
      "originalname": "anchored-boats-ocean-nautical-sailboat-b-2047077.jpg",
      "size": 188115,
      "encoding": "7bit",
      "mimetype": "image/jpeg",
      "annotationStatus": [],
      "refs": [],
      "isBinary": true,
      "executionLogs": {
        "image-preprocess": {
          "default_module": {
            "on_create": {
              "60e2df35985079221279c139": {
                "progress": 100,
                "status": "success"
              }
            }
          }
        }
      },
      "channels": 3,
      "exif": {},
      "height": 853,
      "thumbnailAnnotationsId": "60e2df3533e5ad41a538f45f",
      "thumbnailId": "60e2df3544a226447956b174",
      "width": 1280
    }
  },
  "name": "anchored-boats-ocean-nautical-sailboat-b-2047077.jpg",
  "url": "https://gate.dataloop.ai/api/v1/items/60e2df352ac4725cb2a0f9f9",
  "dataset": "https://gate.dataloop.ai/api/v1/datasets/60e2dab1c09a7cbd614ec5bb",
  "annotationsCount": 4,
  "annotated": true,
  "stream": "https://gate.dataloop.ai/api/v1/items/60e2df352ac4725cb2a0f9f9/stream",
  "thumbnail": "https://gate.dataloop.ai/api/v1/items/60e2df352ac4725cb2a0f9f9/thumbnail",
  "annotations": [
    {
      "id": "60e4612274b4f05a5c0f4436",
      "datasetId": "60e2dab1c09a7cbd614ec5bb",
      "type": "box",
      "label": "boat",
      "attributes": [],
      "coordinates": [
        {
          "x": 228.78,
          "y": 103.24,
          "z": 0
        },
        {
          "x": 574.82,
          "y": 691.01,
          "z": 0
        }
      ],
      "metadata": {
        "system": {
          "status": null,
          "startTime": 0,
          "endTime": 1,
          "frame": 0,
          "endFrame": 1,
          "snapshots_": [],
          "parentId": null,
          "clientId": "1d1bbf57-74ba-42d0-92ec-d35951cbf0fb",
          "automated": false,
          "objectId": "1",
          "isOnlyLocal": false,
          "attributes": {},
          "clientParentId": null,
          "system": false,
          "description": null,
          "itemLinks": [],
          "openAnnotationVersion": "1.5.3-rc.14",
          "recipeId": "60e2dab1de34bdb301f92f11"
        },
        "user": {}
      },
      "creator": "scarpa.mat25@gmail.com",
      "createdAt": "2021-07-06T13:56:50.969Z",
      "updatedBy": "scarpa.mat25@gmail.com",
      "updatedAt": "2021-07-06T13:56:50.969Z",
      "itemId": "60e2df352ac4725cb2a0f9f9",
      "url": "https://gate.dataloop.ai/api/v1/annotations/60e4612274b4f05a5c0f4436",
      "item": "https://gate.dataloop.ai/api/v1/items/60e2df352ac4725cb2a0f9f9",
      "dataset": "https://gate.dataloop.ai/api/v1/datasets/60e2dab1c09a7cbd614ec5bb",
      "hash": "4adcd5882467cdd52367f54316bc13b7a54ee891"
    },
    {
      "id": "60e4612374b4f018bc0f443a",
      "datasetId": "60e2dab1c09a7cbd614ec5bb",
      "type": "box",
      "label": "boat",
      "attributes": [],
      "coordinates": [
        {
          "x": 578.4174740437139,
          "y": 473.02,
          "z": 0
        },
        {
          "x": 703.6,
          "y": 647.8399999999999,
          "z": 0
        }
      ],
      "metadata": {
        "system": {
          "status": null,
          "startTime": 0,
          "endTime": 1,
          "frame": 0,
          "endFrame": 1,
          "snapshots_": [],
          "parentId": null,
          "clientId": "3120a4d7-f518-4ce5-a665-111c8e2b465b",
          "automated": false,
          "objectId": "3",
          "isOnlyLocal": false,
          "attributes": {},
          "clientParentId": null,
          "system": false,
          "description": null,
          "itemLinks": [],
          "openAnnotationVersion": "1.5.3-rc.14",
          "recipeId": "60e2dab1de34bdb301f92f11"
        },
        "user": {}
      },
      "creator": "scarpa.mat25@gmail.com",
      "createdAt": "2021-07-06T13:56:51.069Z",
      "updatedBy": "scarpa.mat25@gmail.com",
      "updatedAt": "2021-07-06T13:56:51.069Z",
      "itemId": "60e2df352ac4725cb2a0f9f9",
      "url": "https://gate.dataloop.ai/api/v1/annotations/60e4612374b4f018bc0f443a",
      "item": "https://gate.dataloop.ai/api/v1/items/60e2df352ac4725cb2a0f9f9",
      "dataset": "https://gate.dataloop.ai/api/v1/datasets/60e2dab1c09a7cbd614ec5bb",
      "hash": "a4c258664ead7062ec8fb9ae626a1747c89bba1b"
    },
    {
      "id": "60e4612374b4f062830f443c",
      "datasetId": "60e2dab1c09a7cbd614ec5bb",
      "type": "box",
      "label": "boat",
      "attributes": [],
      "coordinates": [
        {
          "x": 808.63,
          "y": 332.73,
          "z": 0
        },
        {
          "x": 1067.62,
          "y": 652.87,
          "z": 0
        }
      ],
      "metadata": {
        "system": {
          "status": null,
          "startTime": 0,
          "endTime": 1,
          "frame": 0,
          "endFrame": 1,
          "snapshots_": [],
          "parentId": null,
          "clientId": "2c7b0826-65c1-43e6-93a4-d77509b8b80a",
          "automated": false,
          "objectId": "4",
          "isOnlyLocal": false,
          "attributes": {},
          "clientParentId": null,
          "system": false,
          "description": null,
          "itemLinks": [],
          "openAnnotationVersion": "1.5.3-rc.14",
          "recipeId": "60e2dab1de34bdb301f92f11"
        },
        "user": {}
      },
      "creator": "scarpa.mat25@gmail.com",
      "createdAt": "2021-07-06T13:56:51.115Z",
      "updatedBy": "scarpa.mat25@gmail.com",
      "updatedAt": "2021-07-06T13:56:51.115Z",
      "itemId": "60e2df352ac4725cb2a0f9f9",
      "url": "https://gate.dataloop.ai/api/v1/annotations/60e4612374b4f062830f443c",
      "item": "https://gate.dataloop.ai/api/v1/items/60e2df352ac4725cb2a0f9f9",
      "dataset": "https://gate.dataloop.ai/api/v1/datasets/60e2dab1c09a7cbd614ec5bb",
      "hash": "40f106ac716cb217cc98b68bbdfafe03b813485d"
    },
    {
      "id": "60e4612374b4f06a120f4438",
      "datasetId": "60e2dab1c09a7cbd614ec5bb",
      "type": "box",
      "label": "boat",
      "attributes": [],
      "coordinates": [
        {
          "x": 133.81,
          "y": 399.64,
          "z": 0
        },
        {
          "x": 274.82,
          "y": 665.8299999999999,
          "z": 0
        }
      ],
      "metadata": {
        "system": {
          "status": null,
          "startTime": 0,
          "endTime": 1,
          "frame": 0,
          "endFrame": 1,
          "snapshots_": [],
          "parentId": null,
          "clientId": "33df292d-de4f-4af7-afd7-0ac541abb434",
          "automated": false,
          "objectId": "2",
          "isOnlyLocal": false,
          "attributes": {},
          "clientParentId": null,
          "system": false,
          "description": null,
          "itemLinks": [],
          "openAnnotationVersion": "1.5.3-rc.14",
          "recipeId": "60e2dab1de34bdb301f92f11"
        },
        "user": {}
      },
      "creator": "scarpa.mat25@gmail.com",
      "createdAt": "2021-07-06T13:56:51.019Z",
      "updatedBy": "scarpa.mat25@gmail.com",
      "updatedAt": "2021-07-06T13:56:51.019Z",
      "itemId": "60e2df352ac4725cb2a0f9f9",
      "url": "https://gate.dataloop.ai/api/v1/annotations/60e4612374b4f06a120f4438",
      "item": "https://gate.dataloop.ai/api/v1/items/60e2df352ac4725cb2a0f9f9",
      "dataset": "https://gate.dataloop.ai/api/v1/datasets/60e2dab1c09a7cbd614ec5bb",
      "hash": "69e129179a46b4f3fd5de6ccf9472ac46d74cadd"
    }
  ]
}