{
  "id": "60e2ded4fc56166c748d734e",
  "datasetId": "60e2dab1c09a7cbd614ec5bb",
  "createdAt": "2021-07-05T10:28:36.000Z",
  "dir": "/",
  "filename": "/buoy-sky-coastal-blue-travel-3568365.jpg",
  "type": "file",
  "hidden": false,
  "metadata": {
    "system": {
      "originalname": "buoy-sky-coastal-blue-travel-3568365.jpg",
      "size": 275794,
      "encoding": "7bit",
      "mimetype": "image/jpeg",
      "annotationStatus": [],
      "refs": [],
      "isBinary": true,
      "executionLogs": {
        "image-preprocess": {
          "default_module": {
            "on_create": {
              "60e2ded419e9337de49f5847": {
                "progress": 100,
                "status": "success"
              }
            }
          }
        }
      },
      "channels": 3,
      "exif": {},
      "height": 853,
      "thumbnailAnnotationsId": "60e2ded7cdec2e39b4a940dd",
      "thumbnailId": "60e2ded7c734a8ab06b761af",
      "width": 1280
    }
  },
  "name": "buoy-sky-coastal-blue-travel-3568365.jpg",
  "url": "https://gate.dataloop.ai/api/v1/items/60e2ded4fc56166c748d734e",
  "dataset": "https://gate.dataloop.ai/api/v1/datasets/60e2dab1c09a7cbd614ec5bb",
  "annotationsCount": 1,
  "annotated": true,
  "stream": "https://gate.dataloop.ai/api/v1/items/60e2ded4fc56166c748d734e/stream",
  "thumbnail": "https://gate.dataloop.ai/api/v1/items/60e2ded4fc56166c748d734e/thumbnail",
  "annotations": [
    {
      "id": "60e462dca33564217306e52b",
      "datasetId": "60e2dab1c09a7cbd614ec5bb",
      "type": "class",
      "label": "water",
      "attributes": [],
      "coordinates": null,
      "metadata": {
        "system": {},
        "user": {}
      },
      "creator": "scarpa.mat25@gmail.com",
      "createdAt": "2021-07-06T14:04:12.796Z",
      "updatedBy": "scarpa.mat25@gmail.com",
      "updatedAt": "2021-07-06T14:04:12.796Z",
      "itemId": "60e2ded4fc56166c748d734e",
      "url": "https://gate.dataloop.ai/api/v1/annotations/60e462dca33564217306e52b",
      "item": "https://gate.dataloop.ai/api/v1/items/60e2ded4fc56166c748d734e",
      "dataset": "https://gate.dataloop.ai/api/v1/datasets/60e2dab1c09a7cbd614ec5bb",
      "hash": "96a6c19a80c1167c7ce6512717773bdbf60160cb"
    }
  ]
}